actor/__init__.py
actor/context.py
actor/handler/__init__.py
actor/handler/abc.py
actor/handler/auto.py
actor/response/__init__.py
actor/response/abc.py
actor/response/default.py
actor/response/html.py
actor/tools.py
uvicorn_actor-0.1.2.dist-info/WHEEL
uvicorn_actor-0.1.2.dist-info/METADATA
uvicorn_actor-0.1.2.dist-info/RECORD
