Metadata-Version: 2.1
Name: uvicorn-actor
Version: 0.1.2
Summary: 
Author: timoniq
Requires-Python: >=3.8,<4.0
Classifier: Programming Language :: Python :: 3
Classifier: Programming Language :: Python :: 3.10
Classifier: Programming Language :: Python :: 3.8
Classifier: Programming Language :: Python :: 3.9
Requires-Dist: Jinja2 (>=3.1.2,<4.0.0)
Requires-Dist: aiofiles (>=0.8.0,<0.9.0)
Requires-Dist: uvicorn (>=0.17.6,<0.18.0)
